rockauto_api/__init__.py
rockauto_api/cli.py
rockauto_api/client/__init__.py
rockauto_api/client/base.py
rockauto_api/client/client.py
rockauto_api/client/vehicle.py
rockauto_api/models/__init__.py
rockauto_api/models/account_activity.py
rockauto_api/models/engine.py
rockauto_api/models/order_status.py
rockauto_api/models/part_cache.py
rockauto_api/models/part_category.py
rockauto_api/models/part_info.py
rockauto_api/models/part_search_options.py
rockauto_api/models/part_search_result.py
rockauto_api/models/tool_categories.py
rockauto_api/models/tool_category.py
rockauto_api/models/tool_info.py
rockauto_api/models/tools_result.py
rockauto_api/models/vehicle_engines.py
rockauto_api/models/vehicle_makes.py
rockauto_api/models/vehicle_models.py
rockauto_api/models/vehicle_part_categories.py
rockauto_api/models/vehicle_parts_result.py
rockauto_api/models/vehicle_years.py
rockauto_api/utils/__init__.py
rockauto_api/utils/parsers.py
rockauto_api-1.0.3.dist-info/METADATA
rockauto_api-1.0.3.dist-info/WHEEL
rockauto_api-1.0.3.dist-info/entry_points.txt
rockauto_api-1.0.3.dist-info/RECORD
